ontoxref/__init__.py
ontoxref/backend.py
ontoxref/service.py
ontoxref-1.0.1.dist-info/LICENSE
ontoxref-1.0.1.dist-info/METADATA
ontoxref-1.0.1.dist-info/WHEEL
ontoxref-1.0.1.dist-info/top_level.txt
ontoxref-1.0.1.dist-info/RECORD
