Metadata-Version: 2.1
Name: ontoxref
Version: 1.0.1
Summary: Find mappings (or cross-references) between terms from ontologies and coding standards
Home-page: https://github.com/protegeteam/ontoxref-tool
Author: Josef Hardi
Author-email: josef.hardi@gmail.com
License: UNKNOWN
Project-URL: Bug Tracker, https://github.com/protegeteam/ontoxref-tool/issues
Platform: UNKNOWN
Classifier: Programming Language :: Python :: 3
Classifier: License :: OSI Approved :: BSD License
Classifier: Operating System :: OS Independent
Requires-Python: >=3.6
License-File: LICENSE
Requires-Dist: lmdbm (==0.0.5)
